music_features/.gitkeep
music_features/__init__.py
music_features/_ma_sone.py
music_features/_tension_calculation.py
music_features/dodo.py
music_features/get_alignment.py
music_features/get_beats.py
music_features/get_loudness.py
music_features/get_midi_events.py
music_features/get_onset_velocity.py
music_features/get_sustain.py
music_features/get_tension.py
music_features/util.py
music_features/bin/ErrorDetection.exe
music_features/bin/Fmt3xToHmm.exe
music_features/bin/MatchToCorresp.exe
music_features/bin/MusicXMLToFmt3x.exe
music_features/bin/MusicXMLToHMM.exe
music_features/bin/RealignmentMOHMM.exe
music_features/bin/ScorePerfmMatcher.exe
music_features/bin/SprToFmt3x.exe
music_features/bin/midi2pianoroll.exe
music_features/templates/pyproject.toml
music_features/templates/tension_template.json
cosmodoit-0.1.5.dist-info/LICENSE
cosmodoit-0.1.5.dist-info/METADATA
cosmodoit-0.1.5.dist-info/WHEEL
cosmodoit-0.1.5.dist-info/entry_points.txt
cosmodoit-0.1.5.dist-info/top_level.txt
cosmodoit-0.1.5.dist-info/RECORD
