Metadata-Version: 2.1
Name: cosmodoit
Version: 0.1.5
Summary: Tools suite for music perfomance analysis
Author-email: Corentin Guichaoua <corentin.guichaoua@ircam.fr>, Daniel Bedoya <daniel.bedoya@ircam.fr>
License: GNU GPLv3
Requires-Python: >=3.9
License-File: LICENSE
Requires-Dist: doit >=0.35.0
Requires-Dist: lowess >=1.0.3
Requires-Dist: numpy >=1.22.3
Requires-Dist: pandas >=1.4.2
Requires-Dist: pretty-midi
Requires-Dist: scipy
Requires-Dist: matplotlib
Requires-Dist: soundfile
Requires-Dist: coloredlogs
Requires-Dist: toml
